jetty_scorecard/__init__.py
jetty_scorecard/checks/README.MD
jetty_scorecard/checks/__init__.py
jetty_scorecard/checks/active_masking_policies.py
jetty_scorecard/checks/active_row_access_policies.py
jetty_scorecard/checks/all_checks.py
jetty_scorecard/checks/backup_account_admin.py
jetty_scorecard/checks/common.py
jetty_scorecard/checks/future_grant_coverage.py
jetty_scorecard/checks/has_network_policy.py
jetty_scorecard/checks/inaccessible_tables_and_views.py
jetty_scorecard/checks/inactive_users.py
jetty_scorecard/checks/least_accessible_tables_and_views.py
jetty_scorecard/checks/least_used_tables.py
jetty_scorecard/checks/managed_access_schemas.py
jetty_scorecard/checks/most_accessible_tables_and_views.py
jetty_scorecard/checks/most_used_columns.py
jetty_scorecard/checks/most_used_tables.py
jetty_scorecard/checks/overuse_of_admin_roles.py
jetty_scorecard/checks/password_only_login.py
jetty_scorecard/checks/potentially_sensitive_columns.py
jetty_scorecard/checks/shadow_future_grants.py
jetty_scorecard/checks/templates/active_masking_policies.html.jinja
jetty_scorecard/checks/templates/active_masking_policies_list.html.jinja
jetty_scorecard/checks/templates/active_row_access_policies.html.jinja
jetty_scorecard/checks/templates/active_row_access_policies_list.html.jinja
jetty_scorecard/checks/templates/backup_account_admin.html.jinja
jetty_scorecard/checks/templates/future_grant_coverage.html.jinja
jetty_scorecard/checks/templates/inaccessible_objects.html.jinja
jetty_scorecard/checks/templates/inactive_users.html.jinja
jetty_scorecard/checks/templates/least_accessible_objects.html.jinja
jetty_scorecard/checks/templates/least_used_tables.html.jinja
jetty_scorecard/checks/templates/managed_access_schemas.html.jinja
jetty_scorecard/checks/templates/most_accessible_objects.html.jinja
jetty_scorecard/checks/templates/most_used_columns.html.jinja
jetty_scorecard/checks/templates/most_used_tables.html.jinja
jetty_scorecard-0.1.5.dist-info/entry_points.txt
jetty_scorecard-0.1.5.dist-info/LICENSE
jetty_scorecard-0.1.5.dist-info/WHEEL
jetty_scorecard-0.1.5.dist-info/METADATA
jetty_scorecard-0.1.5.dist-info/RECORD
