Metadata-Version: 2.1
Name: jetty-scorecard
Version: 0.1.5
Summary: 
Author: Isaac Hales
Author-email: isaac.hales@gmail.com
Requires-Python: >=3.8,<4.0
Classifier: Programming Language :: Python :: 3
Classifier: Programming Language :: Python :: 3.8
Classifier: Programming Language :: Python :: 3.9
Classifier: Programming Language :: Python :: 3.10
Classifier: Programming Language :: Python :: 3.11
Requires-Dist: inquirerpy (>=0.3.4,<0.4.0)
Requires-Dist: jinja2 (>=3.1.2,<4.0.0)
Requires-Dist: networkx (>=3.0,<4.0)
Requires-Dist: pandas (>=1.5.3,<2.0.0)
Requires-Dist: snowflake-connector-python (>=2.9.0,<3.0.0)
Requires-Dist: tqdm (>=4.64.1,<5.0.0)
